Workbook

Sheet Assumptions
A1: ASSUMPTIONS BLOCK — every other sheet references these cells
A2: Eswar Mahalingam · International Business Internship (Internship Studio) · Module 6 Project · Export Order Payment & Finance Model
A4: Legend: blue = given input (from brief), yellow fill = editable scenario input, black = formula
A5: Item | B5: Value | C5: Unit | D5: Source / note
A6: TRANSACTION FACTS
A7: Export order value (FOB), USD | B7: 600000 | C7: USD | D7: Brief 3.1
A8: Production cost / packing credit base, USD | B8: 420000 | C8: USD | D8: Brief 3.1
A9: Pre-shipment (production) period, days | B9: 60 | C9: days | D9: Brief 3.1
A10: Credit period offered to buyer, days after shipment | B10: 90 | C10: days | D10: Brief 3.1
A11: Reporting exchange rate, INR per USD | B11: 83.5 | C11: INR/USD | D11: Brief 3.1 (fixed)
A12: Day-count convention, days per year | B12: 360 | C12: days | D12: Brief 3.1
A13: Advance payment price concession | B13: 0.05 | C13: % | D13: Brief 3.4
A14: BANK CHARGES
A15: LC advising charge, USD (flat) | B15: 150 | C15: USD | D15: Brief 3.2
A16: LC confirmation charge, % per month on LC value | B16: 0.0015 | C16: %/month | D16: Brief 3.2
A17: Confirmation tenor, months (LC opened at order, valid to shipment = 60 days) | B17: 2 | C17: months | D17: Assumption: 60-day production = 2 months
A18: Negotiation / handling charge, % of bill value | B18: 0.002 | C18: % | D18: Brief 3.2
A19: SWIFT / courier, USD (flat) | B19: 120 | C19: USD | D19: Brief 3.2
A20: Documentary collection (D/A) handling, % of bill value | B20: 0.0015 | C20: % | D20: Brief 3.2
A21: Open account remittance handling, USD (flat) | B21: 150 | C21: USD | D21: Brief 3.2
A22: Inward remittance charge (advance), USD (flat) | B22: 100 | C22: USD | D22: Brief 3.2
A23: Discrepancy fee (LC), USD per set | B23: 90 | C23: USD | D23: Brief 3.2
A24: FINANCE RATES (per year)
A25: Pre-shipment packing credit rate | B25: 0.09 | C25: % | D25: Brief 3.3
A26: Post-shipment credit / bill discounting (INR) rate | B26: 0.095 | C26: % | D26: Brief 3.3
A27: Interest subvention benefit (reduction) | B27: 0.03 | C27: % | D27: Brief 3.3
A28: Foreign currency usance bill discount rate | B28: 0.065 | C28: % | D28: Brief 3.3 (already net)
A29: Exporter opportunity cost of capital (PV rate) | B29: 0.12 | C29: % | D29: Brief 3.3
A30: Subvented packing credit rate | B30: =B25-B27 -> 0.06 | C30: % | D30: Formula: base − subvention
A31: Subvented post-shipment credit rate | B31: =B26-B27 -> 0.065 | C31: % | D31: Formula: base − subvention
A32: DEFAULT PROBABILITIES
A33: Advance payment (100%) | B33: 0 | C33: % | D33: Brief 3.4
A34: Confirmed LC at sight | B34: 0.002 | C34: % | D34: Brief 3.4
A35: Usance LC 90 days (unconfirmed) | B35: 0.01 | C35: % | D35: Brief 3.4
A36: Documentary collection D/A 90 days | B36: 0.04 | C36: % | D36: Brief 3.4
A37: Open account 90 days | B37: 0.08 | C37: % | D37: Brief 3.4
A38: TASK E SCENARIO INPUTS
A39: Number of discrepant document sets presented | B39: 1 | C39: sets | D39: Task E scenario
A40: Default probability if LC is discrepant (bank undertaking lost → buyer credit risk, open-account level) | B40: 0.08 | C40: % | D40: Scenario (editable)
A41: Extra days delay while buyer waiver is sought | B41: 10 | C41: days | D41: Scenario (editable)

Sheet TaskA_PackingCredit
A1: TASK A — Pre-shipment financing cost (packing credit)
A2: Eswar Mahalingam · International Business Internship (Internship Studio) · Module 6 Project · Export Order Payment & Finance Model
A4: Step | B4: Item | C4: Value | D4: Formula (as typed)
A5: 1 | B5: Packing credit principal, USD | C5: =Assumptions!$B$8 -> 420000 | D5: =Assumptions!B8
A6: 2 | B6: Base packing credit rate | C6: =Assumptions!$B$25 -> 0.09 | D6: =Assumptions!B25
A7: 3 | B7: Interest subvention | C7: =Assumptions!$B$27 -> 0.03 | D7: =Assumptions!B27
A8: 4 | B8: Subvented rate (base − subvention) | C8: =C6-C7 -> 0.06 | D8: =C6-C7
A9: 5 | B9: Production period, days | C9: =Assumptions!$B$9 -> 60 | D9: =Assumptions!B9
A10: 6 | B10: Day count | C10: =Assumptions!$B$12 -> 360 | D10: =Assumptions!B12
A11: 7 | B11: Packing credit interest, USD = Principal × subvented rate × days/360 | C11: =C5*C8*C9/C10 -> 4200 | D11: =C5*C8*C9/C10
A12: 8 | B12: Packing credit interest, INR (× 83.50) | C12: =C11*Assumptions!$B$11 -> 350700 | D12: =C11*Assumptions!B11
A13: 9 | B13: Interest without subvention (for comparison), USD | C13: =C5*C6*C9/C10 -> 6300 | D13: =C5*C6*C9/C10
A14: 10 | B14: Subvention saving, USD | C14: =C13-C11 -> 2100 | D14: =C13-C11
A16: Note: this cost applies to every payment term except advance payment (cash arrives before production, so no packing credit is drawn).

Sheet TaskB_C_Model
A1: TASK B & C — Cost build-up, net realisation, present value and all-in cost for the five payment terms
A2: Eswar Mahalingam · International Business Internship (Internship Studio) · Module 6 Project · Export Order Payment & Finance Model
A4: Row | B4: Advance payment (100%) | C4: Confirmed LC at sight | D4: Usance LC 90 days (unconfirmed) | E4: Documentary collection D/A 90 days | F4: Open account 90 days
A5: Special condition | B5: 5% price concession demanded by buyer | C5: Confirmation charge applies | D5: Bill discounted in foreign currency @ 6.5% | E5: No bank undertaking; post-shipment credit | F5: No documents held; post-shipment credit
A6: Payment timing (day) | B6: 0 | C6: =Assumptions!$B$9 -> 60 | D6: =Assumptions!$B$9 -> 60 | E6: =Assumptions!$B$9 -> 60 | F6: =Assumptions!$B$9 -> 60
A7: Cash timing basis | B7: Advance received before production | C7: Sight payment at shipment (day 60) | D7: Discounted proceeds at shipment (day 60) | E7: Credit-financed proceeds at shipment (day 60) | F7: Credit-financed proceeds at shipment (day 60)
A8: GROSS AMOUNT RECEIVED | B8: =Assumptions!$B$7*(1-Assumptions!$B$13) -> 570000 | C8: =Assumptions!$B$7 -> 600000 | D8: =Assumptions!$B$7 -> 600000 | E8: =Assumptions!$B$7 -> 600000 | F8: =Assumptions!$B$7 -> 600000
A9: Bank charge: LC advising | B9: 0 | C9: =Assumptions!$B$15 -> 150 | D9: =Assumptions!$B$15 -> 150 | E9: 0 | F9: 0
A10: Bank charge: LC confirmation (0.15%/month × months × LC value) | B10: 0 | C10: =Assumptions!$B$16*Assumptions!$B$17*Assumptions!$B$7 -> 1800 | D10: 0 | E10: 0 | F10: 0
A11: Bank charge: negotiation / handling (0.20% × bill) | B11: 0 | C11: =Assumptions!$B$18*Assumptions!$B$7 -> 1200 | D11: =Assumptions!$B$18*Assumptions!$B$7 -> 1200 | E11: 0 | F11: 0
A12: Bank charge: D/A collection handling (0.15% × bill) | B12: 0 | C12: 0 | D12: 0 | E12: =Assumptions!$B$20*Assumptions!$B$7 -> 900 | F12: 0
A13: Bank charge: open account remittance handling | B13: 0 | C13: 0 | D13: 0 | E13: 0 | F13: =Assumptions!$B$21 -> 150
A14: Bank charge: inward remittance (advance) | B14: =Assumptions!$B$22 -> 100 | C14: 0 | D14: 0 | E14: 0 | F14: 0
A15: Bank charge: SWIFT / courier | B15: 0 | C15: =Assumptions!$B$19 -> 120 | D15: =Assumptions!$B$19 -> 120 | E15: =Assumptions!$B$19 -> 120 | F15: =Assumptions!$B$19 -> 120
A16: TOTAL BANK CHARGES | B16: =SUM(B9:B15) -> 100 | C16: =SUM(C9:C15) -> 3270 | D16: =SUM(D9:D15) -> 1470 | E16: =SUM(E9:E15) -> 1020 | F16: =SUM(F9:F15) -> 270
A17: Financing / discounting cost (usance LC: bill × 6.5% × 90/360; D/A & OA: bill × subvented 6.5% × 90/360) | B17: 0 | C17: 0 | D17: =Assumptions!$B$7*Assumptions!$B$28*Assumptions!$B$10/Assumptions!$B$12 -> 9750 | E17: =Assumptions!$B$7*Assumptions!$B$31*Assumptions!$B$10/Assumptions!$B$12 -> 9750 | F17: =Assumptions!$B$7*Assumptions!$B$31*Assumptions!$B$10/Assumptions!$B$12 -> 9750
A18: Packing credit cost (Task A) | B18: 0 | C18: =TaskA_PackingCredit!$C$11 -> 4200 | D18: =TaskA_PackingCredit!$C$11 -> 4200 | E18: =TaskA_PackingCredit!$C$11 -> 4200 | F18: =TaskA_PackingCredit!$C$11 -> 4200
A19: Default probability | B19: =Assumptions!$B$33 -> 0 | C19: =Assumptions!$B$34 -> 0.002 | D19: =Assumptions!$B$35 -> 0.01 | E19: =Assumptions!$B$36 -> 0.04 | F19: =Assumptions!$B$37 -> 0.08
A20: Expected loss = probability × order value | B20: =B19*Assumptions!$B$7 -> 0 | C20: =C19*Assumptions!$B$7 -> 1200 | D20: =D19*Assumptions!$B$7 -> 6000 | E20: =E19*Assumptions!$B$7 -> 24000 | F20: =F19*Assumptions!$B$7 -> 48000
A21: NET REALISATION (nominal) = gross − charges − financing − packing credit − expected loss | B21: =B8-B16-B17-B18-B20 -> 569900 | C21: =C8-C16-C17-C18-C20 -> 591330 | D21: =D8-D16-D17-D18-D20 -> 578580 | E21: =E8-E16-E17-E18-E20 -> 561030 | F21: =F8-F16-F17-F18-F20 -> 537780
A22: Net realisation, INR (× 83.50) | B22: =B21*Assumptions!$B$11 -> 47586650 | C22: =C21*Assumptions!$B$11 -> 49376055 | D22: =D21*Assumptions!$B$11 -> 48311430 | E22: =E21*Assumptions!$B$11 -> 46846005 | F22: =F21*Assumptions!$B$11 -> 44904630
A23: Days from day 0 to cash | B23: =B6 -> 0 | C23: =C6 -> 60 | D23: =D6 -> 60 | E23: =E6 -> 60 | F23: =F6 -> 60
A24: PV factor (simple) = 1 / (1 + 12% × days/360) | B24: =1/(1+Assumptions!$B$29*B23/Assumptions!$B$12) -> 1 | C24: =1/(1+Assumptions!$B$29*C23/Assumptions!$B$12) -> 0.98039216 | D24: =1/(1+Assumptions!$B$29*D23/Assumptions!$B$12) -> 0.98039216 | E24: =1/(1+Assumptions!$B$29*E23/Assumptions!$B$12) -> 0.98039216 | F24: =1/(1+Assumptions!$B$29*F23/Assumptions!$B$12) -> 0.98039216
A25: PRESENT VALUE OF NET REALISATION, USD | B25: =B21*B24 -> 569900 | C25: =C21*C24 -> 579735.29 | D25: =D21*D24 -> 567235.29 | E25: =E21*E24 -> 550029.41 | F25: =F21*F24 -> 527235.29
A26: Present value, INR | B26: =B25*Assumptions!$B$11 -> 47586650 | C26: =C25*Assumptions!$B$11 -> 48407897 | D26: =D25*Assumptions!$B$11 -> 47364147 | E26: =E25*Assumptions!$B$11 -> 45927456 | F26: =F25*Assumptions!$B$11 -> 44024147
A27: ALL-IN COST % = (order value − PV) / order value | B27: =(Assumptions!$B$7-B25)/Assumptions!$B$7 -> 0.050166667 | C27: =(Assumptions!$B$7-C25)/Assumptions!$B$7 -> 0.03377451 | D27: =(Assumptions!$B$7-D25)/Assumptions!$B$7 -> 0.054607843 | E27: =(Assumptions!$B$7-E25)/Assumptions!$B$7 -> 0.083284314 | F27: =(Assumptions!$B$7-F25)/Assumptions!$B$7 -> 0.12127451
A28: All-in cost, USD (order value − PV) | B28: =Assumptions!$B$7-B25 -> 30100 | C28: =Assumptions!$B$7-C25 -> 20264.706 | D28: =Assumptions!$B$7-D25 -> 32764.706 | E28: =Assumptions!$B$7-E25 -> 49970.588 | F28: =Assumptions!$B$7-F25 -> 72764.706
A29: Rank by PV of net realisation (1 = best) | B29: =RANK(B25,$B$25:$F$25,0) -> 2 | C29: =RANK(C25,$B$25:$F$25,0) -> 1 | D29: =RANK(D25,$B$25:$F$25,0) -> 3 | E29: =RANK(E25,$B$25:$F$25,0) -> 4 | F29: =RANK(F25,$B$25:$F$25,0) -> 5
A30: Rank by default risk (1 = safest) | B30: =RANK(B19,$B$19:$F$19,1) -> 1 | C30: =RANK(C19,$B$19:$F$19,1) -> 2 | D30: =RANK(D19,$B$19:$F$19,1) -> 3 | E30: =RANK(E19,$B$19:$F$19,1) -> 4 | F30: =RANK(F19,$B$19:$F$19,1) -> 5
A31: Cost of risk share: expected loss as % of all-in cost | B31: =IF(B28=0,0,B20/B28) -> 0 | C31: =IF(C28=0,0,C20/C28) -> 0.059216255 | D31: =IF(D28=0,0,D20/D28) -> 0.18312388 | E31: =IF(E28=0,0,E20/E28) -> 0.48028252 | F31: =IF(F28=0,0,F20/F28) -> 0.65966047
A37: Checks
A38: Advance premium check: does the 5% concession (USD) exceed total sight-LC frictions (charges + packing credit + expected loss)? | B38: =Assumptions!$B$7*Assumptions!$B$13 -> 30000 | C38: =C16+C18+C20 -> 8670 | D38: =IF(B38>C38,"YES — concession costs more than sight LC","NO") -> YES — concession costs more than sight LC
A39: Best term by PV (formula) | B39: =INDEX($B$4:$F$4,MATCH(1,$B$29:$F$29,0)) -> Confirmed LC at sight
A40: Safest term by default risk (formula) | B40: =INDEX($B$4:$F$4,MATCH(1,$B$30:$F$30,0)) -> Advance payment (100%)
A41: PV gap: best term minus second-best, USD | B41: =LARGE($B$25:$F$25,1)-LARGE($B$25:$F$25,2) -> 9835.2941

Sheet TaskD_Summary
A1: TASK D — Ranking, comparison table and chart
A2: Eswar Mahalingam · International Business Internship (Internship Studio) · Module 6 Project · Export Order Payment & Finance Model
A4: Payment term | B4: Default probability | C4: Expected loss (USD) | D4: Net realisation nominal (USD) | E4: PV of net realisation (USD) | F4: PV (INR) | G4: All-in cost % | H4: Rank by PV | I4: Rank by risk | J4: Verdict
A5: =TaskB_C_Model!B4 -> Advance payment (100%) | B5: =TaskB_C_Model!B19 -> 0 | C5: =TaskB_C_Model!B20 -> 0 | D5: =TaskB_C_Model!B21 -> 569900 | E5: =TaskB_C_Model!B25 -> 569900 | F5: =TaskB_C_Model!B26 -> 47586650 | G5: =TaskB_C_Model!B27 -> 0.050166667 | H5: =TaskB_C_Model!B29 -> 2 | I5: =TaskB_C_Model!B30 -> 1 | J5: =IF(H5=1,"RECOMMENDED",IF(H5=2,"Runner-up",IF(B5>=0.04,"Reject — risk too high","Acceptable fallback"))) -> Runner-up
A6: =TaskB_C_Model!C4 -> Confirmed LC at sight | B6: =TaskB_C_Model!C19 -> 0.002 | C6: =TaskB_C_Model!C20 -> 1200 | D6: =TaskB_C_Model!C21 -> 591330 | E6: =TaskB_C_Model!C25 -> 579735.29 | F6: =TaskB_C_Model!C26 -> 48407897 | G6: =TaskB_C_Model!C27 -> 0.03377451 | H6: =TaskB_C_Model!C29 -> 1 | I6: =TaskB_C_Model!C30 -> 2 | J6: =IF(H6=1,"RECOMMENDED",IF(H6=2,"Runner-up",IF(B6>=0.04,"Reject — risk too high","Acceptable fallback"))) -> RECOMMENDED
A7: =TaskB_C_Model!D4 -> Usance LC 90 days (unconfirmed) | B7: =TaskB_C_Model!D19 -> 0.01 | C7: =TaskB_C_Model!D20 -> 6000 | D7: =TaskB_C_Model!D21 -> 578580 | E7: =TaskB_C_Model!D25 -> 567235.29 | F7: =TaskB_C_Model!D26 -> 47364147 | G7: =TaskB_C_Model!D27 -> 0.054607843 | H7: =TaskB_C_Model!D29 -> 3 | I7: =TaskB_C_Model!D30 -> 3 | J7: =IF(H7=1,"RECOMMENDED",IF(H7=2,"Runner-up",IF(B7>=0.04,"Reject — risk too high","Acceptable fallback"))) -> Acceptable fallback
A8: =TaskB_C_Model!E4 -> Documentary collection D/A 90 days | B8: =TaskB_C_Model!E19 -> 0.04 | C8: =TaskB_C_Model!E20 -> 24000 | D8: =TaskB_C_Model!E21 -> 561030 | E8: =TaskB_C_Model!E25 -> 550029.41 | F8: =TaskB_C_Model!E26 -> 45927456 | G8: =TaskB_C_Model!E27 -> 0.083284314 | H8: =TaskB_C_Model!E29 -> 4 | I8: =TaskB_C_Model!E30 -> 4 | J8: =IF(H8=1,"RECOMMENDED",IF(H8=2,"Runner-up",IF(B8>=0.04,"Reject — risk too high","Acceptable fallback"))) -> Reject — risk too high
A9: =TaskB_C_Model!F4 -> Open account 90 days | B9: =TaskB_C_Model!F19 -> 0.08 | C9: =TaskB_C_Model!F20 -> 48000 | D9: =TaskB_C_Model!F21 -> 537780 | E9: =TaskB_C_Model!F25 -> 527235.29 | F9: =TaskB_C_Model!F26 -> 44024147 | G9: =TaskB_C_Model!F27 -> 0.12127451 | H9: =TaskB_C_Model!F29 -> 5 | I9: =TaskB_C_Model!F30 -> 5 | J9: =IF(H9=1,"RECOMMENDED",IF(H9=2,"Runner-up",IF(B9>=0.04,"Reject — risk too high","Acceptable fallback"))) -> Reject — risk too high
A11: Recommended structure: | B11: =TaskB_C_Model!B39 -> Confirmed LC at sight
A12: Advance PV shortfall vs recommended, USD: | B12: =E6-E5 -> 9835.2941
A13: Open account PV shortfall vs recommended, USD: | B13: =E6-E9 -> 52500
A14: Is advance payment really best once the concession is counted? | B14: =IF(E5>=MAX(E5:E9),"Yes","No — the 5% concession (USD 30,000) costs more than every friction on the sight LC combined") -> No — the 5% concession (USD 30,000) costs more than every friction on the sight LC combined

Sheet TaskE_UCP600
A1: TASK E — UCP 600 documentary check on the confirmed sight LC presentation and its financial impact
A2: Eswar Mahalingam · International Business Internship (Internship Studio) · Module 6 Project · Export Order Payment & Finance Model
A4: # | B4: Document / item presented | C4: LC requirement | D4: Presented as | E4: Discrepancy? | F4: UCP 600 basis | G4: Why it fails
A5: 1 | B5: Commercial invoice | C5: Signed invoice for the LC amount (USD 600,000) | D5: Shows USD 605,000 | E5: YES | F5: Art. 18(b) — a nominated/confirming bank may refuse an invoice issued for an amount in excess of the credit; Art. 14(d) data must not conflict | G5: Invoice exceeds the LC amount by USD 5,000; no ±tolerance wording ("about"/"approximately") in the LC (Art. 30).
A6: 2 | B6: Ocean bill of lading | C6: Full set of CLEAN SHIPPED ON BOARD B/L | D6: Marked "received for shipment" | E6: YES | F6: Art. 20(a)(ii) — B/L must indicate goods shipped on board a named vessel by pre-printed wording or an on-board notation with date | G6: "Received for shipment" only proves receipt by the carrier, not loading; no on-board date, so shipment cannot be evidenced.
A7: 3 | B7: Marine insurance policy | C7: Cover for 110% of CIF value | D7: Covers 100% of value | E7: YES | F7: Art. 28(f)(ii) — minimum cover is 110% of CIF/CIP value when the credit so requires (and even by default) | G7: Under-insured by 10 percentage points; the bank/buyer are not protected for the full landed value plus expected profit.
A8: 4 | B8: Certificate of origin | C8: Consistent with other documents | D8: Consistent | E8: NO | F8: Art. 14(d)/(e) — data need not be identical but must not conflict | G8: Complies — no action.
A9: 5 | B9: Shipment date | C9: On or before the LC's latest shipment date | D9: Later than the latest shipment date | E9: YES | F9: Art. 14(c) and the LC's latest-shipment field (MT700 44C); late shipment is a classic discrepancy | G9: Documents dated after the latest shipment date cannot be honoured; also risks the Art. 14(c) 21-day presentation window and LC expiry.
A10: 6 | B10: Packing list & sight bill of exchange | C10: Required | D10: Presented (no issue stated) | E10: NO | F10: Art. 14 | G10: Complies — no action.
A12: Number of discrepancies found | B12: =COUNTIF(E5:E10,"YES") -> 4
A13: Discrepancy fee, USD (USD 90 × sets) | B13: =Assumptions!$B$23*Assumptions!$B$39 -> 90
A15: FINANCIAL IMPACT ON THE SIGHT LC OPTION
A16: Line | B16: Compliant presentation | C16: Discrepant presentation | D16: Change | E16: Explanation
A17: Default probability | B17: =TaskB_C_Model!C19 -> 0.002 | C17: =Assumptions!$B$40 -> 0.08 | D17: =C17-B17 -> 0.078 | E17: Bank undertaking is lost (Art. 16 refusal) — payment now depends on the buyer's waiver, i.e. the buyer's own credit risk (open-account level).
A18: Expected loss, USD | B18: =B17*Assumptions!$B$7 -> 1200 | C18: =C17*Assumptions!$B$7 -> 48000 | D18: =C18-B18 -> 46800 | E18: Probability × exposure.
A19: Discrepancy fee, USD | B19: 0 | C19: =B13 -> 90 | D19: =C19-B19 -> 90 | E19: USD 90 per set presented.
A20: Days to cash | B20: =Assumptions!$B$9 -> 60 | C20: =Assumptions!$B$9+Assumptions!$B$41 -> 70 | D20: =C20-B20 -> 10 | E20: Waiver / re-presentation delay (scenario input).
A21: Net realisation (nominal), USD | B21: =TaskB_C_Model!C21 -> 591330 | C21: =B21-D18-D19 -> 544440 | D21: =C21-B21 -> -46890 | E21: Extra expected loss and fee reduce the nominal figure.
A22: PV factor | B22: =TaskB_C_Model!C24 -> 0.98039216 | C22: =1/(1+Assumptions!$B$29*C20/Assumptions!$B$12) -> 0.9771987 | D22: =C22-B22 -> -0.0031934598 | E22: Longer wait lowers the PV factor.
A23: PV of net realisation, USD | B23: =B21*B22 -> 579735.29 | C23: =C21*C22 -> 532026.06 | D23: =C23-B23 -> -47709.235 | E23: Combined effect.
A24: All-in cost % | B24: =(Assumptions!$B$7-B23)/Assumptions!$B$7 -> 0.03377451 | C24: =(Assumptions!$B$7-C23)/Assumptions!$B$7 -> 0.1132899 | D24: =C24-B24 -> 0.079515392 | E24: Sight LC drifts from best option to open-account-like economics.
A25: Rank among the five terms (PV) | B25: =TaskB_C_Model!C29 -> 1 | C25: =1+COUNTIF(TaskB_C_Model!$B$25:$F$25,">"&C23)-IF(C23<TaskB_C_Model!C25,1,0) -> 4 | D25: =C25-B25 -> 3 | E25: Recomputed rank of the discrepant LC against the other four terms.
A27: Cure actions: (1) re-issue invoice at USD 600,000; (2) obtain on-board notation with date on the B/L; (3) endorse insurance to 110% CIF; (5) request LC amendment extending latest shipment date and expiry BEFORE presenting — then the presentation is compliant and the confirming bank's undertaking is restored.

Sheet Sensitivity
A1: SENSITIVITY — how the ranking moves with cost of capital and open-account default risk (all live formulas)
A2: Eswar Mahalingam · International Business Internship (Internship Studio) · Module 6 Project · Export Order Payment & Finance Model
A4: PV of net realisation (USD) at different exporter costs of capital
A5: Payment term | B5: 0.08 | C5: 0.1 | D5: 0.12 | E5: 0.14 | F5: 0.16
A6: =TaskB_C_Model!B4 -> Advance payment (100%) | B6: =TaskB_C_Model!B21/(1+B$5*TaskB_C_Model!B23/Assumptions!$B$12) -> 569900 | C6: =TaskB_C_Model!B21/(1+C$5*TaskB_C_Model!B23/Assumptions!$B$12) -> 569900 | D6: =TaskB_C_Model!B21/(1+D$5*TaskB_C_Model!B23/Assumptions!$B$12) -> 569900 | E6: =TaskB_C_Model!B21/(1+E$5*TaskB_C_Model!B23/Assumptions!$B$12) -> 569900 | F6: =TaskB_C_Model!B21/(1+F$5*TaskB_C_Model!B23/Assumptions!$B$12) -> 569900
A7: =TaskB_C_Model!C4 -> Confirmed LC at sight | B7: =TaskB_C_Model!C21/(1+B$5*TaskB_C_Model!C23/Assumptions!$B$12) -> 583549.34 | C7: =TaskB_C_Model!C21/(1+C$5*TaskB_C_Model!C23/Assumptions!$B$12) -> 581636.07 | D7: =TaskB_C_Model!C21/(1+D$5*TaskB_C_Model!C23/Assumptions!$B$12) -> 579735.29 | E7: =TaskB_C_Model!C21/(1+E$5*TaskB_C_Model!C23/Assumptions!$B$12) -> 577846.91 | F7: =TaskB_C_Model!C21/(1+F$5*TaskB_C_Model!C23/Assumptions!$B$12) -> 575970.78
A8: =TaskB_C_Model!D4 -> Usance LC 90 days (unconfirmed) | B8: =TaskB_C_Model!D21/(1+B$5*TaskB_C_Model!D23/Assumptions!$B$12) -> 570967.11 | C8: =TaskB_C_Model!D21/(1+C$5*TaskB_C_Model!D23/Assumptions!$B$12) -> 569095.08 | D8: =TaskB_C_Model!D21/(1+D$5*TaskB_C_Model!D23/Assumptions!$B$12) -> 567235.29 | E8: =TaskB_C_Model!D21/(1+E$5*TaskB_C_Model!D23/Assumptions!$B$12) -> 565387.62 | F8: =TaskB_C_Model!D21/(1+F$5*TaskB_C_Model!D23/Assumptions!$B$12) -> 563551.95
A9: =TaskB_C_Model!E4 -> Documentary collection D/A 90 days | B9: =TaskB_C_Model!E21/(1+B$5*TaskB_C_Model!E23/Assumptions!$B$12) -> 553648.03 | C9: =TaskB_C_Model!E21/(1+C$5*TaskB_C_Model!E23/Assumptions!$B$12) -> 551832.79 | D9: =TaskB_C_Model!E21/(1+D$5*TaskB_C_Model!E23/Assumptions!$B$12) -> 550029.41 | E9: =TaskB_C_Model!E21/(1+E$5*TaskB_C_Model!E23/Assumptions!$B$12) -> 548237.79 | F9: =TaskB_C_Model!E21/(1+F$5*TaskB_C_Model!E23/Assumptions!$B$12) -> 546457.79
A10: =TaskB_C_Model!F4 -> Open account 90 days | B10: =TaskB_C_Model!F21/(1+B$5*TaskB_C_Model!F23/Assumptions!$B$12) -> 530703.95 | C10: =TaskB_C_Model!F21/(1+C$5*TaskB_C_Model!F23/Assumptions!$B$12) -> 528963.93 | D10: =TaskB_C_Model!F21/(1+D$5*TaskB_C_Model!F23/Assumptions!$B$12) -> 527235.29 | E10: =TaskB_C_Model!F21/(1+E$5*TaskB_C_Model!F23/Assumptions!$B$12) -> 525517.92 | F10: =TaskB_C_Model!F21/(1+F$5*TaskB_C_Model!F23/Assumptions!$B$12) -> 523811.69
A12: Best term at each rate | B12: =INDEX($A$6:$A$10,MATCH(MAX(B6:B10),B6:B10,0)) -> Confirmed LC at sight | C12: =INDEX($A$6:$A$10,MATCH(MAX(C6:C10),C6:C10,0)) -> Confirmed LC at sight | D12: =INDEX($A$6:$A$10,MATCH(MAX(D6:D10),D6:D10,0)) -> Confirmed LC at sight | E12: =INDEX($A$6:$A$10,MATCH(MAX(E6:E10),E6:E10,0)) -> Confirmed LC at sight | F12: =INDEX($A$6:$A$10,MATCH(MAX(F6:F10),F6:F10,0)) -> Confirmed LC at sight
A14: Break-even default probability at which open account would equal the sight LC on PV
A15: OA net realisation before expected loss, USD | B15: =TaskB_C_Model!F8-TaskB_C_Model!F16-TaskB_C_Model!F17-TaskB_C_Model!F18 -> 585780
A16: Required OA net realisation to match sight-LC PV, USD | B16: =TaskB_C_Model!C25/TaskB_C_Model!F24 -> 591330
A17: Break-even default probability | B17: =(B15-B16)/Assumptions!$B$7 -> -0.00925
A18: Interpretation | B18: =IF(B17<0,"Open account can never beat the sight LC even at zero default risk","Open account only wins if the buyer default probability is below the break-even shown") -> Open account can never beat the sight LC even at zero default risk
A20: Advance concession break-even: concession % at which advance payment equals sight-LC PV | B20: =1-(TaskB_C_Model!C25+Assumptions!$B$22)/Assumptions!$B$7 -> 0.033607843
A21: Interpretation | B21: ="Advance beats the sight LC only if the buyer's concession is below "&TEXT(B20,"0.00%")&" (buyer demands 5.00%)" -> Advance beats the sight LC only if the buyer's concession is below 3.36% (buyer demands 5.00%)
